<annotation>
  <folder/>
  <filename>IMG_0868.jpg</filename>
  <database/>
  <annotation/>
  <image/>
  <size>
    <height>4000</height>
    <width>6000</width>
    <depth>3</depth>
  </size>
  <segmented/>
  <object>
    <name>nums_4</name>
    <pose/>
    <truncated/>
    <difficult/>
    <bndbox>
      <xmin>2479.166666666667</xmin>
      <ymin>1790.2777777777778</ymin>
      <xmax>2830.5555555555557</xmax>
      <ymax>2291.666666666667</ymax>
    </bndbox>
  </object>
  <object>
    <name>nums_1</name>
    <pose/>
    <truncated/>
    <difficult/>
    <bndbox>
      <xmin>2847.222222222222</xmin>
      <ymin>1793.0555555555557</ymin>
      <xmax>3162.5</xmax>
      <ymax>2288.888888888889</ymax>
    </bndbox>
  </object>
  <object>
    <name>nums_10</name>
    <pose/>
    <truncated/>
    <difficult/>
    <bndbox>
      <xmin>3175.0</xmin>
      <ymin>1794.4444444444446</ymin>
      <xmax>3493.0555555555557</xmax>
      <ymax>2283.3333333333335</ymax>
    </bndbox>
  </object>
</annotation>
