<annotation>
  <folder/>
  <filename>img_0931.jpg</filename>
  <database/>
  <annotation/>
  <image/>
  <size>
    <height>500</height>
    <width>500</width>
    <depth>3</depth>
  </size>
  <segmented/>
  <object>
    <name>5</name>
    <pose/>
    <truncated/>
    <difficult/>
    <bndbox>
      <xmin>239.8230088495575</xmin>
      <ymin>244.24778761061944</ymin>
      <xmax>278.76106194690266</xmax>
      <ymax>311.50442477876106</ymax>
    </bndbox>
  </object>
  <object>
    <name>2</name>
    <pose/>
    <truncated/>
    <difficult/>
    <bndbox>
      <xmin>281.1971108227958</xmin>
      <ymin>244.60176991150442</ymin>
      <xmax>319.42719931837104</xmax>
      <ymax>311.1504424778761</ymax>
    </bndbox>
  </object>
  <object>
    <name>3</name>
    <pose/>
    <truncated/>
    <difficult/>
    <bndbox>
      <xmin>321.23893805309734</xmin>
      <ymin>242.8318584070796</ymin>
      <xmax>358.75273522975925</xmax>
      <ymax>305.90809628008753</ymax>
    </bndbox>
  </object>
</annotation>
