<annotation>
  <folder/>
  <filename>img_0913.jpg</filename>
  <database/>
  <annotation/>
  <image/>
  <size>
    <height>500</height>
    <width>500</width>
    <depth>3</depth>
  </size>
  <segmented/>
  <object>
    <name>4</name>
    <pose/>
    <truncated/>
    <difficult/>
    <bndbox>
      <xmin>221.67381974248926</xmin>
      <ymin>266.9527896995708</ymin>
      <xmax>259.2274678111588</xmax>
      <ymax>331.3304721030043</ymax>
    </bndbox>
  </object>
  <object>
    <name>9</name>
    <pose/>
    <truncated/>
    <difficult/>
    <bndbox>
      <xmin>261.3733905579399</xmin>
      <ymin>266.52360515021456</ymin>
      <xmax>299.3562231759657</xmax>
      <ymax>331.7596566523605</ymax>
    </bndbox>
  </object>
  <object>
    <name>9</name>
    <pose/>
    <truncated/>
    <difficult/>
    <bndbox>
      <xmin>301.7167381974249</xmin>
      <ymin>265.45064377682405</ymin>
      <xmax>339.48497854077254</xmax>
      <ymax>330.0429184549356</ymax>
    </bndbox>
  </object>
</annotation>
