<annotation>
  <folder/>
  <filename>img_0523.jpg</filename>
  <database/>
  <annotation/>
  <image/>
  <size>
    <height>500</height>
    <width>500</width>
    <depth>3</depth>
  </size>
  <segmented/>
  <object>
    <name>10</name>
    <pose/>
    <truncated/>
    <difficult/>
    <bndbox>
      <xmin>206.30914826498423</xmin>
      <ymin>188.01261829652998</ymin>
      <xmax>247.63406940063092</xmax>
      <ymax>261.8296529968454</ymax>
    </bndbox>
  </object>
  <object>
    <name>9</name>
    <pose/>
    <truncated/>
    <difficult/>
    <bndbox>
      <xmin>249.21135646687696</xmin>
      <ymin>188.6435331230284</ymin>
      <xmax>291.4826498422713</xmax>
      <ymax>262.46056782334387</ymax>
    </bndbox>
  </object>
  <object>
    <name>5</name>
    <pose/>
    <truncated/>
    <difficult/>
    <bndbox>
      <xmin>293.3753943217666</xmin>
      <ymin>188.6435331230284</ymin>
      <xmax>335.9621451104101</xmax>
      <ymax>262.77602523659306</ymax>
    </bndbox>
  </object>
</annotation>
