<annotation>
  <folder/>
  <filename>img_0709.jpg</filename>
  <database/>
  <annotation/>
  <image/>
  <size>
    <height>500</height>
    <width>500</width>
    <depth>3</depth>
  </size>
  <segmented/>
  <object>
    <name>3</name>
    <pose/>
    <truncated/>
    <difficult/>
    <bndbox>
      <xmin>231.11587982832617</xmin>
      <ymin>197.8540772532189</ymin>
      <xmax>268.6695278969957</xmax>
      <ymax>260.08583690987126</ymax>
    </bndbox>
  </object>
  <object>
    <name>1</name>
    <pose/>
    <truncated/>
    <difficult/>
    <bndbox>
      <xmin>270.3862660944206</xmin>
      <ymin>197.63948497854076</ymin>
      <xmax>308.15450643776825</xmax>
      <ymax>260.08583690987126</ymax>
    </bndbox>
  </object>
  <object>
    <name>3</name>
    <pose/>
    <truncated/>
    <difficult/>
    <bndbox>
      <xmin>309.656652360515</xmin>
      <ymin>196.99570815450645</ymin>
      <xmax>348.92703862660943</xmax>
      <ymax>260.30042918454933</ymax>
    </bndbox>
  </object>
</annotation>
