<annotation>
  <folder/>
  <filename>img_0410.jpg</filename>
  <database/>
  <annotation/>
  <image/>
  <size>
    <height>500</height>
    <width>500</width>
    <depth>3</depth>
  </size>
  <segmented/>
  <object>
    <name>1</name>
    <pose/>
    <truncated/>
    <difficult/>
    <bndbox>
      <xmin>230.20833333333334</xmin>
      <ymin>155.98958333333334</ymin>
      <xmax>267.70833333333337</xmax>
      <ymax>230.46875</ymax>
    </bndbox>
  </object>
  <object>
    <name>5</name>
    <pose/>
    <truncated/>
    <difficult/>
    <bndbox>
      <xmin>269.53125</xmin>
      <ymin>158.33333333333334</ymin>
      <xmax>311.45833333333337</xmax>
      <ymax>231.51041666666669</ymax>
    </bndbox>
  </object>
  <object>
    <name>10</name>
    <pose/>
    <truncated/>
    <difficult/>
    <bndbox>
      <xmin>313.5416666666667</xmin>
      <ymin>159.63541666666669</ymin>
      <xmax>355.98958333333337</xmax>
      <ymax>231.77083333333334</ymax>
    </bndbox>
  </object>
</annotation>
