<annotation>
  <folder/>
  <filename>img_0592.jpg</filename>
  <database/>
  <annotation/>
  <image/>
  <size>
    <height>500</height>
    <width>500</width>
    <depth>3</depth>
  </size>
  <segmented/>
  <object>
    <name>10</name>
    <pose/>
    <truncated/>
    <difficult/>
    <bndbox>
      <xmin>246.6876971608833</xmin>
      <ymin>169.4006309148265</ymin>
      <xmax>288.6435331230284</xmax>
      <ymax>236.2776025236593</ymax>
    </bndbox>
  </object>
  <object>
    <name>4</name>
    <pose/>
    <truncated/>
    <difficult/>
    <bndbox>
      <xmin>290.22082018927443</xmin>
      <ymin>165.93059936908517</ymin>
      <xmax>333.7539432176656</xmax>
      <ymax>236.90851735015772</ymax>
    </bndbox>
  </object>
  <object>
    <name>2</name>
    <pose/>
    <truncated/>
    <difficult/>
    <bndbox>
      <xmin>335.64668769716087</xmin>
      <ymin>164.66876971608832</ymin>
      <xmax>381.0725552050473</xmax>
      <ymax>236.2776025236593</ymax>
    </bndbox>
  </object>
</annotation>
