<annotation>
  <folder/>
  <filename>img_0372.jpg</filename>
  <database/>
  <annotation/>
  <image/>
  <size>
    <height>500</height>
    <width>500</width>
    <depth>3</depth>
  </size>
  <segmented/>
  <object>
    <name>1</name>
    <pose/>
    <truncated/>
    <difficult/>
    <bndbox>
      <xmin>253.00859598853867</xmin>
      <ymin>156.44699140401144</ymin>
      <xmax>288.25214899713467</xmax>
      <ymax>228.65329512893982</ymax>
    </bndbox>
  </object>
  <object>
    <name>8</name>
    <pose/>
    <truncated/>
    <difficult/>
    <bndbox>
      <xmin>294.55587392550143</xmin>
      <ymin>156.73352435530086</ymin>
      <xmax>336.67621776504296</xmax>
      <ymax>227.79369627507162</ymax>
    </bndbox>
  </object>
  <object>
    <name>4</name>
    <pose/>
    <truncated/>
    <difficult/>
    <bndbox>
      <xmin>339.25501432664754</xmin>
      <ymin>156.44699140401144</ymin>
      <xmax>382.23495702005727</xmax>
      <ymax>227.5071633237822</ymax>
    </bndbox>
  </object>
</annotation>
