<annotation>
  <folder/>
  <filename>img_0339.jpg</filename>
  <database/>
  <annotation/>
  <image/>
  <size>
    <height>500</height>
    <width>500</width>
    <depth>3</depth>
  </size>
  <segmented/>
  <object>
    <name>1</name>
    <pose/>
    <truncated/>
    <difficult/>
    <bndbox>
      <xmin>226.88888888888889</xmin>
      <ymin>182.29166666666669</ymin>
      <xmax>258.48611111111114</xmax>
      <ymax>253.81944444444446</ymax>
    </bndbox>
  </object>
  <object>
    <name>9</name>
    <pose/>
    <truncated/>
    <difficult/>
    <bndbox>
      <xmin>263.34722222222223</xmin>
      <ymin>182.63888888888889</ymin>
      <xmax>305.0138888888889</xmax>
      <ymax>255.9027777777778</ymax>
    </bndbox>
  </object>
  <object>
    <name>3</name>
    <pose/>
    <truncated/>
    <difficult/>
    <bndbox>
      <xmin>307.44444444444446</xmin>
      <ymin>181.59722222222223</ymin>
      <xmax>350.15277777777777</xmax>
      <ymax>255.55555555555557</ymax>
    </bndbox>
  </object>
</annotation>
