<annotation>
  <folder/>
  <filename>img_0557.jpg</filename>
  <database/>
  <annotation/>
  <image/>
  <size>
    <height>500</height>
    <width>500</width>
    <depth>3</depth>
  </size>
  <segmented/>
  <object>
    <name>10</name>
    <pose/>
    <truncated/>
    <difficult/>
    <bndbox>
      <xmin>187.65277777777777</xmin>
      <ymin>234.72222222222223</ymin>
      <xmax>232.09722222222223</xmax>
      <ymax>307.2916666666667</ymax>
    </bndbox>
  </object>
  <object>
    <name>1</name>
    <pose/>
    <truncated/>
    <difficult/>
    <bndbox>
      <xmin>234.18055555555557</xmin>
      <ymin>233.68055555555557</ymin>
      <xmax>274.80555555555554</xmax>
      <ymax>307.98611111111114</ymax>
    </bndbox>
  </object>
  <object>
    <name>6</name>
    <pose/>
    <truncated/>
    <difficult/>
    <bndbox>
      <xmin>278.27777777777777</xmin>
      <ymin>233.33333333333334</ymin>
      <xmax>322.375</xmax>
      <ymax>308.68055555555554</ymax>
    </bndbox>
  </object>
</annotation>
